mformat/__init__.py
mformat/factory.py
mformat/mformat.py
mformat/mformat_html.py
mformat/mformat_lists_impl.py
mformat/mformat_md.py
mformat/mformat_state.py
mformat/mformat_textbased.py
mformat/py.typed
mformat/reg_pkg_formats.py
mformat-0.2.2.dist-info/METADATA
mformat-0.2.2.dist-info/WHEEL
mformat-0.2.2.dist-info/top_level.txt
mformat-0.2.2.dist-info/RECORD
