Metadata-Version: 2.4
Name: mformat
Version: 0.2.2
Summary: Uniform way to write simple text to different file formats
Author: Tom Björkholm
Author-email: Tom Björkholm <klausuler_linnet0q@icloud.com>
License-Expression: MIT
Project-URL: Source code, https://bitbucket.org/tom-bjorkholm/mformat
Classifier: Programming Language :: Python :: 3
Classifier: Operating System :: OS Independent
Requires-Python: >=3.12
Requires-Dist: pip
Requires-Dist: setuptools
Requires-Dist: build
Requires-Dist: wheel
Dynamic: author
Dynamic: requires-dist
Dynamic: requires-python
